[
  {
    "id": 9,
    "linkedin_url": "https://www.linkedin.com/in/scottbreitenother/",
    "name": "Scott Breitenother",
    "headline": "Co-Founder & CEO at Kilo Code",
    "company": "Kilo Code",
    "product_description": "Open-source AI coding agent - 500K+ downloads on VS Code and JetBrains",
    "stage": "seed",
    "funding": "8M seed",
    "pain_points": "competing with Cursor/Copilot, open source monetization",
    "growth_signals": "#1 Product of the Day on Product Hunt, 500K+ downloads",
    "recent_posts": "Open source AI coding agent ecosystem",
    "personalization_hooks": "Co-founded with GitLab co-founder. Open-source dev tools founder."
  },
  {
    "id": 10,
    "linkedin_url": "https://www.linkedin.com/in/benbartling/",
    "name": "Ben Bartling",
    "headline": "Startup Founder, Full-Stack Developer",
    "company": "ZoomShift (exited)",
    "product_description": "Built, grew, and sold a bootstrapped SaaS (ZoomShift - employee scheduling)",
    "stage": "bootstrapped",
    "growth_signals": "Successful exit, serial founder",
    "personalization_hooks": "Bootstrapped SaaS founder who exited. Knows the early-stage grind."
  },
  {
    "id": 11,
    "linkedin_url": "https://www.linkedin.com/in/erangalperin/",
    "name": "Eran Galperin",
    "headline": "Bootstrapped to 8-figure exit | Operator, mentor & investor in B2B SaaS",
    "company": "Gymdesk (exited)",
    "product_description": "Previously founded Gymdesk (gym management SaaS) - bootstrapped to 8-figure exit",
    "stage": "bootstrapped",
    "growth_signals": "8-figure exit, now mentor and investor",
    "personalization_hooks": "Bootstrapped SaaS legend. Now mentoring/investing - extremely valuable feedback."
  },
  {
    "id": 12,
    "linkedin_url": "https://www.linkedin.com/in/henry-purchase/",
    "name": "Henry Purchase",
    "headline": "Founder at ROUGH WATER MEDIA",
    "company": "New SaaS (pre-launch)",
    "product_description": "Building a new SaaS with 1000+ people on waitlist, zero ad spend",
    "stage": "pre-seed",
    "growth_signals": "1000+ waitlist with no ad spend",
    "personalization_hooks": "Pre-launch founder with strong organic traction. Both in the early grind."
  },
  {
    "id": 13,
    "linkedin_url": "https://www.linkedin.com/in/tibo-the-maker/",
    "name": "Tibo Louis-Lucas",
    "headline": "Growing a 100m bootstrapped SaaS",
    "company": "Tweet Hunter / Taplio",
    "product_description": "LinkedIn and Twitter growth tools for creators and founders",
    "stage": "bootstrapped",
    "growth_signals": "Scaling toward 100M goal, major creator-economy SaaS",
    "recent_posts": "LinkedIn growth strategies, SaaS building in public",
    "personalization_hooks": "Massive LinkedIn presence, builds tools for the exact audience we target."
  },
  {
    "id": 14,
    "linkedin_url": "https://www.linkedin.com/in/justinjagiello/",
    "name": "Justin Jagiello",
    "headline": "SaaS Founder",
    "company": "Active SaaS Builder",
    "product_description": "Active SaaS founder in the developer/builder community",
    "stage": "unknown",
    "personalization_hooks": "Active in SaaS founder LinkedIn community"
  },
  {
    "id": 15,
    "linkedin_url": "https://www.linkedin.com/in/logan-grim/",
    "name": "Logan Grim",
    "headline": "Consultant | B2B SaaS Founder",
    "company": "B2B SaaS (consulting + product)",
    "product_description": "B2B SaaS founder and consultant",
    "stage": "bootstrapped",
    "personalization_hooks": "B2B SaaS founder, understands the early-stage feedback loop"
  },
  {
    "id": 3,
    "linkedin_url": "https://www.linkedin.com/in/dctanner/",
    "name": "Damien C. Tanner",
    "headline": "CEO & Co-Founder at Layercode",
    "company": "Layercode",
    "product_description": "Voice AI infrastructure for developers - build low-latency voice agents with TypeScript",
    "stage": "seed",
    "location": "London",
    "website": "https://layercode.com",
    "pain_points": "developer onboarding, competing in crowded voice AI space",
    "growth_signals": "#3 Product of the Day on Product Hunt, launched CLI tool",
    "recent_posts": "Writing about voice AI prompting and developer experience",
    "personalization_hooks": "20 years building infrastructure and dev tools. Fellow dev-tools founder."
  },
  {
    "id": 4,
    "linkedin_url": "https://www.linkedin.com/in/suptejas/",
    "name": "Tejas Ravishankar",
    "headline": "Founder at Dimension",
    "company": "Dimension",
    "product_description": "Proactive AI assistant for engineering teams - removes context-switching",
    "stage": "seed",
    "location": "Dubai",
    "pain_points": "enterprise adoption, explaining proactive AI to skeptical devs",
    "growth_signals": "#2 Product of the Day on Product Hunt, went GA recently",
    "recent_posts": "Launched from stealth on Product Hunt successfully",
    "personalization_hooks": "Building for engineering teams, adjacent audience to globalize.now users"
  },
  {
    "id": 5,
    "linkedin_url": "https://www.linkedin.com/in/nikita-sorokin40/",
    "name": "Nikita Sorokin",
    "headline": "Co-Founder at Loki.Build",
    "company": "Loki.Build",
    "product_description": "AI-native landing page builder - studio-grade pages from prompts",
    "stage": "bootstrapped",
    "location": "Barcelona",
    "website": "https://loki.build",
    "pain_points": "competing with Webflow/Framer, differentiation in AI builder space",
    "growth_signals": "#2 Product of the Month on Product Hunt Dec 2025",
    "recent_posts": "Product Hunt launch strategy content",
    "personalization_hooks": "8+ years leading design teams at startups. Both building AI-powered dev/creator tools."
  },
  {
    "id": 6,
    "linkedin_url": "https://www.linkedin.com/in/brandonfoo/",
    "name": "Brandon Foo",
    "headline": "CEO & Co-Founder of Paragon",
    "company": "Paragon",
    "product_description": "Embedded integration platform for SaaS apps - the Plaid of SaaS integrations",
    "stage": "series-a",
    "funding": "21M total across 3 rounds",
    "location": "Los Angeles",
    "website": "https://useparagon.com",
    "pain_points": "developer adoption vs build-it-yourself mentality",
    "growth_signals": "100+ customers, 45+ integrations, 2x YC alum",
    "recent_posts": "SaaS integration ecosystem content",
    "personalization_hooks": "10+ year SaaS founder, 2x YC alum. Experienced founder who could give great product feedback."
  },
  {
    "id": 7,
    "linkedin_url": "https://www.linkedin.com/in/rabisg/",
    "name": "Rabi Shanker Guha",
    "headline": "CEO & Co-Founder at Thesys",
    "company": "Thesys",
    "product_description": "Generative UI platform - C1 GenUI API for AI-driven interfaces",
    "stage": "seed",
    "funding": "4M led by Together Fund",
    "pain_points": "explaining GenUI concept to market, developer adoption",
    "growth_signals": "#1 Developer Tool of the Week on Product Hunt, 3 successful launches",
    "recent_posts": "Generative UI and AI interface design content",
    "personalization_hooks": "Ex-Google, ex-DevRev. Building AI-native dev tools like us."
  },
  {
    "id": 8,
    "linkedin_url": "https://www.linkedin.com/in/parikshitd/",
    "name": "Parikshit Deshmukh",
    "headline": "Co-Founder at Thesys",
    "company": "Thesys",
    "product_description": "Generative UI platform - C1 GenUI API for AI-driven interfaces",
    "stage": "seed",
    "funding": "4M led by Together Fund",
    "growth_signals": "#1 Developer Tool of the Week on Product Hunt",
    "personalization_hooks": "Technical co-founder at Thesys, building AI dev tools"
  }
]
